[{"packageName":"com.sleepycat.je.dbi","className":"DiskOrderedCursorImpl","methodSignature":"<init>([Lcom/sleepycat/je/dbi/DatabaseImpl;Lcom/sleepycat/je/DiskOrderedCursorConfig;)V","bytecodeIndex":105,"javaLine":160,"options":["KEYSONLY"],"optionCount":1},{"packageName":"com.sleepycat.analysis","className":"ScanCGDepth","methodSignature":"<init>([Ljava/lang/String;)V","bytecodeIndex":171,"javaLine":145,"options":["KEYSONLY"],"optionCount":1},{"packageName":"com.sleepycat.analysis","className":"ScanCGDepth","methodSignature":"checkData(Lcom/sleepycat/je/DatabaseEntry;)V","bytecodeIndex":28,"javaLine":396,"options":["KEYSONLY"],"optionCount":1},{"packageName":"com.sleepycat.je.dbi","className":"DiskOrderedCursorImpl","methodSignature":"<init>([Lcom/sleepycat/je/dbi/DatabaseImpl;Lcom/sleepycat/je/DiskOrderedCursorConfig;)V","bytecodeIndex":105,"javaLine":160,"options":["KEYSONLY"],"optionCount":1},{"packageName":"com.sleepycat.analysis","className":"ScanCGDepth","methodSignature":"dirtyReadScan()V","bytecodeIndex":20,"javaLine":319,"options":["KEYSONLY"],"optionCount":1},{"packageName":"com.sleepycat.analysis","className":"ScanCGDepth","methodSignature":"checkEquals(Ljava/lang/Object;Ljava/lang/Object;)V","bytecodeIndex":9,"javaLine":413,"options":["KEYSONLY"],"optionCount":1},{"packageName":"com.sleepycat.je.dbi","className":"DiskOrderedScanner","methodSignature":"<init>([Lcom/sleepycat/je/dbi/DatabaseImpl;Lcom/sleepycat/je/dbi/DiskOrderedScanner$RecordProcessor;ZZZZJJZ)V","bytecodeIndex":236,"javaLine":639,"options":["KEYSONLY"],"optionCount":1},{"packageName":"com.sleepycat.je.dbi","className":"DiskOrderedScanner","methodSignature":"<init>([Lcom/sleepycat/je/dbi/DatabaseImpl;Lcom/sleepycat/je/dbi/DiskOrderedScanner$RecordProcessor;ZZZZJJZ)V","bytecodeIndex":68,"javaLine":609,"options":["KEYSONLY"],"optionCount":1},{"packageName":"com.sleepycat.je.dbi","className":"DiskOrderedScanner","methodSignature":"<init>([Lcom/sleepycat/je/dbi/DatabaseImpl;Lcom/sleepycat/je/dbi/DiskOrderedScanner$RecordProcessor;ZZZZJJZ)V","bytecodeIndex":89,"javaLine":610,"options":["KEYSONLY"],"optionCount":1},{"packageName":"com.sleepycat.analysis","className":"ScanCGDepth","methodSignature":"checkEquals(Ljava/lang/Object;Ljava/lang/Object;)V","bytecodeIndex":1,"javaLine":412,"options":["KEYSONLY"],"optionCount":1},{"packageName":"com.sleepycat.je","className":"Database","methodSignature":"trace(Ljava/util/logging/Level;Ljava/lang/String;Lcom/sleepycat/je/Transaction;Ljava/lang/Object;)V","bytecodeIndex":65,"javaLine":2485,"options":["KEYSONLY"],"optionCount":1},{"packageName":"com.sleepycat.je.dbi","className":"DiskOrderedScanner","methodSignature":"<init>([Lcom/sleepycat/je/dbi/DatabaseImpl;Lcom/sleepycat/je/dbi/DiskOrderedScanner$RecordProcessor;ZZZZJJZ)V","bytecodeIndex":99,"javaLine":610,"options":["KEYSONLY"],"optionCount":1},{"packageName":"com.sleepycat.je.dbi","className":"DiskOrderedCursorImpl","methodSignature":"<init>([Lcom/sleepycat/je/dbi/DatabaseImpl;Lcom/sleepycat/je/DiskOrderedCursorConfig;)V","bytecodeIndex":119,"javaLine":161,"options":["KEYSONLY"],"optionCount":1},{"packageName":"com.sleepycat.analysis","className":"ScanCGDepth","methodSignature":"dirtyReadScan()V","bytecodeIndex":85,"javaLine":332,"options":["KEYSONLY"],"optionCount":1},{"packageName":"com.sleepycat.je.dbi","className":"DiskOrderedScanner","methodSignature":"<init>([Lcom/sleepycat/je/dbi/DatabaseImpl;Lcom/sleepycat/je/dbi/DiskOrderedScanner$RecordProcessor;ZZZZJJZ)V","bytecodeIndex":94,"javaLine":610,"options":["KEYSONLY"],"optionCount":1},{"packageName":"com.sleepycat.analysis","className":"ScanCGDepth","methodSignature":"diskOrderedScan()V","bytecodeIndex":89,"javaLine":353,"options":["KEYSONLY"],"optionCount":1},{"packageName":"com.sleepycat.je.dbi","className":"DiskOrderedCursorImpl","methodSignature":"<init>([Lcom/sleepycat/je/dbi/DatabaseImpl;Lcom/sleepycat/je/DiskOrderedCursorConfig;)V","bytecodeIndex":119,"javaLine":161,"options":["KEYSONLY"],"optionCount":1},{"packageName":"com.sleepycat.je","className":"Database","methodSignature":"openCursor(Lcom/sleepycat/je/DiskOrderedCursorConfig;)Lcom/sleepycat/je/DiskOrderedCursor;","bytecodeIndex":11,"javaLine":971,"options":["KEYSONLY"],"optionCount":1},{"packageName":"com.sleepycat.analysis","className":"ScanCGDepth","methodSignature":"checkEquals(Ljava/lang/Object;Ljava/lang/Object;)V","bytecodeIndex":13,"javaLine":413,"options":["KEYSONLY"],"optionCount":1},{"packageName":"com.sleepycat.analysis","className":"ScanCGDepth","methodSignature":"checkData(Lcom/sleepycat/je/DatabaseEntry;)V","bytecodeIndex":28,"javaLine":396,"options":["KEYSONLY"],"optionCount":1},{"packageName":"com.sleepycat.je.dbi","className":"DiskOrderedCursorImpl","methodSignature":"<init>([Lcom/sleepycat/je/dbi/DatabaseImpl;Lcom/sleepycat/je/DiskOrderedCursorConfig;)V","bytecodeIndex":95,"javaLine":159,"options":["KEYSONLY"],"optionCount":1},{"packageName":"com.sleepycat.je.dbi","className":"DiskOrderedScanner","methodSignature":"<init>([Lcom/sleepycat/je/dbi/DatabaseImpl;Lcom/sleepycat/je/dbi/DiskOrderedScanner$RecordProcessor;ZZZZJJZ)V","bytecodeIndex":82,"javaLine":610,"options":["KEYSONLY"],"optionCount":1},{"packageName":"com.sleepycat.analysis","className":"ScanCGDepth","methodSignature":"checkEquals(Ljava/lang/Object;Ljava/lang/Object;)V","bytecodeIndex":5,"javaLine":412,"options":["KEYSONLY"],"optionCount":1},{"packageName":"com.sleepycat.analysis","className":"ScanCGDepth","methodSignature":"checkEquals(Ljava/lang/Object;Ljava/lang/Object;)V","bytecodeIndex":53,"javaLine":417,"options":["KEYSONLY"],"optionCount":1},{"packageName":"com.sleepycat.je.dbi","className":"DiskOrderedScanner","methodSignature":"<init>([Lcom/sleepycat/je/dbi/DatabaseImpl;Lcom/sleepycat/je/dbi/DiskOrderedScanner$RecordProcessor;ZZZZJJZ)V","bytecodeIndex":63,"javaLine":609,"options":["KEYSONLY"],"optionCount":1}]