[
  {
    "packageName": "com.googlecode.pngtastic.core",
    "className": "PngColorCounter",
    "methodSignature": "<com.googlecode.pngtastic.core.PngColorCounter: getColors(Lcom/googlecode/pngtastic/core/PngImage;Ljava/util/List;J)Ljava/util/List;>",
    "bytecodeIndex": 698,
    "options": [
      "FREQTHRESHOLD"
    ]
  },
  {
    "packageName": "com.googlecode.pngtastic",
    "className": "PngtasticColorCounter",
    "methodSignature": "<com.googlecode.pngtastic.PngtasticColorCounter: <init>([Ljava/lang/String;Ljava/lang/String;DDIJ)V>",
    "bytecodeIndex": 25,
    "options": [
      "FREQTHRESHOLD"
    ]
  },
  {
    "packageName": "com.googlecode.pngtastic",
    "className": "PngtasticColorCounter",
    "methodSignature": "<com.googlecode.pngtastic.PngtasticColorCounter: main([Ljava/lang/String;)V>",
    "bytecodeIndex": 230,
    "options": [
      "FREQTHRESHOLD"
    ]
  }
]