[{"path":[{"className":"edu.cmu.cs.mvelezce.taint.programs.Interaction0","javaLineNumber":18},{"className":"edu.cmu.cs.mvelezce.taint.programs.Interaction0","javaLineNumber":24}]},{"path":[{"className":"edu.cmu.cs.mvelezce.taint.programs.Interaction0","javaLineNumber":18},{"className":"edu.cmu.cs.mvelezce.taint.programs.Interaction0","javaLineNumber":24},{"className":"edu.cmu.cs.mvelezce.taint.programs.Interaction0","javaLineNumber":25},{"className":"edu.cmu.cs.mvelezce.taint.programs.Interaction0","javaLineNumber":32},{"className":"edu.cmu.cs.mvelezce.taint.programs.Interaction0","javaLineNumber":37},{"className":"edu.cmu.cs.mvelezce.taint.programs.Interaction0","javaLineNumber":37}]}]