[{"path":[{"className":"edu.cmu.cs.mvelezce.taint.programs.Interaction7","javaLineNumber":14},{"className":"edu.cmu.cs.mvelezce.taint.programs.Interaction7","javaLineNumber":18},{"className":"edu.cmu.cs.mvelezce.taint.programs.Interaction7","javaLineNumber":19},{"className":"edu.cmu.cs.mvelezce.taint.programs.Interaction7","javaLineNumber":23}]},{"path":[{"className":"edu.cmu.cs.mvelezce.taint.programs.Interaction7","javaLineNumber":14},{"className":"edu.cmu.cs.mvelezce.taint.programs.Interaction7","javaLineNumber":18}]}]