[{"packageName":"edu.cmu.cs.mvelezce.taint.programs","className":"Basic13$W","methodSignature":"<edu.cmu.cs.mvelezce.taint.programs.Basic13$W: analyze()V>","bytecodeIndex":4,"javaLine":112,"options":["A"],"optionCount":1},{"packageName":"edu.cmu.cs.mvelezce.taint.programs","className":"Basic13","methodSignature":"<edu.cmu.cs.mvelezce.taint.programs.Basic13: main([Ljava/lang/String;)V>","bytecodeIndex":85,"javaLine":45,"options":["A"],"optionCount":1},{"packageName":"edu.cmu.cs.mvelezce.taint.programs","className":"Basic13$W","methodSignature":"<edu.cmu.cs.mvelezce.taint.programs.Basic13$W: analyze()V>","bytecodeIndex":22,"javaLine":116,"options":["B"],"optionCount":1},{"packageName":"edu.cmu.cs.mvelezce.taint.programs","className":"Basic13","methodSignature":"<edu.cmu.cs.mvelezce.taint.programs.Basic13: main([Ljava/lang/String;)V>","bytecodeIndex":90,"javaLine":46,"options":["B"],"optionCount":1},{"packageName":"edu.cmu.cs.mvelezce.taint.programs","className":"Basic13","methodSignature":"<edu.cmu.cs.mvelezce.taint.programs.Basic13: <init>(ZZZ)V>","bytecodeIndex":27,"javaLine":57,"options":["A","B","C"],"optionCount":3},{"packageName":"edu.cmu.cs.mvelezce.taint.programs","className":"Basic13","methodSignature":"<edu.cmu.cs.mvelezce.taint.programs.Basic13: main([Ljava/lang/String;)V>","bytecodeIndex":95,"javaLine":47,"options":["C"],"optionCount":1},{"packageName":"edu.cmu.cs.mvelezce.taint.programs","className":"Basic13","methodSignature":"<edu.cmu.cs.mvelezce.taint.programs.Basic13: <init>(ZZZ)V>","bytecodeIndex":84,"javaLine":69,"options":["C"],"optionCount":1},{"packageName":"edu.cmu.cs.mvelezce.taint.programs","className":"Basic13","methodSignature":"<edu.cmu.cs.mvelezce.taint.programs.Basic13: <init>(ZZZ)V>","bytecodeIndex":46,"javaLine":61,"options":["A"],"optionCount":1},{"packageName":"edu.cmu.cs.mvelezce.taint.programs","className":"Basic13","methodSignature":"<edu.cmu.cs.mvelezce.taint.programs.Basic13: <init>(ZZZ)V>","bytecodeIndex":65,"javaLine":65,"options":["B"],"optionCount":1},{"packageName":"edu.cmu.cs.mvelezce.taint.programs","className":"Basic13$W","methodSignature":"<edu.cmu.cs.mvelezce.taint.programs.Basic13$W: analyze()V>","bytecodeIndex":40,"javaLine":120,"options":["C"],"optionCount":1}]